ckanapi_harvesters/__init__.py
ckanapi_harvesters/auxiliary/__init__.py
ckanapi_harvesters/auxiliary/ckan_action.py
ckanapi_harvesters/auxiliary/ckan_api_key.py
ckanapi_harvesters/auxiliary/ckan_auxiliary.py
ckanapi_harvesters/auxiliary/ckan_configuration.py
ckanapi_harvesters/auxiliary/ckan_defs.py
ckanapi_harvesters/auxiliary/ckan_errors.py
ckanapi_harvesters/auxiliary/ckan_map.py
ckanapi_harvesters/auxiliary/ckan_model.py
ckanapi_harvesters/auxiliary/ckan_vocabulary_deprecated.py
ckanapi_harvesters/auxiliary/deprecated.py
ckanapi_harvesters/auxiliary/error_level_message.py
ckanapi_harvesters/auxiliary/external_code_import.py
ckanapi_harvesters/auxiliary/list_records.py
ckanapi_harvesters/auxiliary/login.py
ckanapi_harvesters/auxiliary/path.py
ckanapi_harvesters/auxiliary/proxy_config.py
ckanapi_harvesters/auxiliary/urls.py
ckanapi_harvesters/builder/__init__.py
ckanapi_harvesters/builder/builder_aux.py
ckanapi_harvesters/builder/builder_ckan.py
ckanapi_harvesters/builder/builder_errors.py
ckanapi_harvesters/builder/builder_field.py
ckanapi_harvesters/builder/builder_package.py
ckanapi_harvesters/builder/builder_package_1_basic.py
ckanapi_harvesters/builder/builder_package_2_harvesters.py
ckanapi_harvesters/builder/builder_package_3_multi_threaded.py
ckanapi_harvesters/builder/builder_package_example.xlsx
ckanapi_harvesters/builder/builder_resource.py
ckanapi_harvesters/builder/builder_resource_datastore.py
ckanapi_harvesters/builder/builder_resource_datastore_multi_abc.py
ckanapi_harvesters/builder/builder_resource_datastore_multi_folder.py
ckanapi_harvesters/builder/builder_resource_datastore_multi_harvester.py
ckanapi_harvesters/builder/builder_resource_datastore_unmanaged.py
ckanapi_harvesters/builder/builder_resource_datastore_url.py
ckanapi_harvesters/builder/builder_resource_init.py
ckanapi_harvesters/builder/builder_resource_multi_abc.py
ckanapi_harvesters/builder/builder_resource_multi_datastore.py
ckanapi_harvesters-0.0.3.dist-info/METADATA
ckanapi_harvesters-0.0.3.dist-info/WHEEL
ckanapi_harvesters-0.0.3.dist-info/top_level.txt
ckanapi_harvesters-0.0.3.dist-info/RECORD
