Metadata-Version: 2.4
Name: ckanapi_harvesters
Version: 0.0.3
Summary: Package helping to upload local resources to a CKAN server using the CKAN API. Metadata and the list of resources can be defined in an Excel spreadsheet. The package includes requests to download resources and checks metadata against formatting rules.
Author-email: ifpen-gp <63413841+ifpen-gp@users.noreply.github.com>
Maintainer-email: ifpen-gp <63413841+ifpen-gp@users.noreply.github.com>
License: MIT License
Project-URL: Documentation, https://mobidec.github.io/ckanapi_harvesters/index.html
Project-URL: Repository, https://github.com/Mobidec/ckanapi_harvesters.git
Project-URL: Issues, https://github.com/Mobidec/ckanapi_harvesters/issues
Classifier: Programming Language :: Python :: 3.10
Classifier: License :: OSI Approved :: MIT License
Classifier: Operating System :: OS Independent
Requires-Python: >=3.10
Requires-Dist: pytest==8.0.1
Requires-Dist: myst-nb>=1.3.0
Requires-Dist: requests>=2.32.5
Requires-Dist: pandas>=2.3.3
Requires-Dist: numpy>=2.2.6
Requires-Dist: openpyxl>=3.1.5
Provides-Extra: extras
Requires-Dist: pymongo>=4.8.0; extra == "extras"
Requires-Dist: psycopg2>=2.9.11; extra == "extras"
Requires-Dist: shapely>=2.1.2; extra == "extras"
Requires-Dist: pyproj==3.6.1; extra == "extras"
Requires-Dist: geopandas>=1.1.2; extra == "extras"
Provides-Extra: harvesters
Requires-Dist: pymongo>=4.8.0; extra == "harvesters"
Requires-Dist: psycopg2>=2.9.11; extra == "harvesters"
Requires-Dist: shapely>=2.1.2; extra == "harvesters"
Requires-Dist: pyproj==3.6.1; extra == "harvesters"
Provides-Extra: alt
Requires-Dist: bson; extra == "alt"
Requires-Dist: shapely>=2.1.2; extra == "alt"
Requires-Dist: pyproj==3.6.1; extra == "alt"
Requires-Dist: geopandas>=1.1.2; extra == "alt"
